{
  "tasks": [
    {
      "id": 2,
      "text": "do123asd",
      "day": "feb 51th at 3:00pm",
      "reminder": false
    },
    {
      "id": 3,
      "text": "d234234ocasd",
      "day": "feb 54th at 3:00pm",
      "reminder": false
    },
    {
      "text": "123",
      "day": "123",
      "reminder": true,
      "id": 4
    },
    {
      "text": "123",
      "day": "123",
      "reminder": true,
      "id": 5
    },
    {
      "text": "2355",
      "day": "4324234",
      "reminder": true,
      "id": 6
    },
    {
      "text": "123",
      "day": "123",
      "reminder": false,
      "id": 7
    }
  ]
}